.gitignore
LICENSE
README
setup.py
deferred/__init__.py
deferred/_defer.py
deferred/_failure.py
deferred/_reflect.py
deferred/_util.py
deferred.egg-info/PKG-INFO
deferred.egg-info/SOURCES.txt
deferred.egg-info/dependency_links.txt
deferred.egg-info/top_level.txt
deferred/tests/__init__.py
deferred/tests/generator_failure_tests.py
deferred/tests/test_defer.py
deferred/tests/test_defgen.py
deferred/tests/test_failure.py
deferred/tests/test_reflect.py